{"ge_cloud_id": null, "expectations": [{"expectation_type": "expect_table_columns_to_match_set", "kwargs": {"column_set": ["season", "Date", "HomeTeam", "AwayTeam", "FTHG", "FTAG", "FTR"]}, "meta": {}}, {"expectation_type": "expect_column_values_to_be_of_type", "kwargs": {"column": "season", "type_": "str"}, "meta": {}}, {"expectation_type": "expect_column_values_to_be_null", "kwargs": {"column": "season", "mostly": 0}, "meta": {}}, {"expectation_type": "expect_column_values_to_be_of_type", "kwargs": {"column": "Date", "type_": "str"}, "meta": {}}, {"expectation_type": "expect_column_values_to_be_null", "kwargs": {"column": "Date", "mostly": 0}, "meta": {}}, {"expectation_type": "expect_column_values_to_be_of_type", "kwargs": {"column": "HomeTeam", "type_": "str"}, "meta": {}}, {"expectation_type": "expect_column_values_to_be_null", "kwargs": {"column": "HomeTeam", "mostly": 0}, "meta": {}}, {"expectation_type": "expect_column_values_to_be_of_type", "kwargs": {"column": "AwayTeam", "type_": "str"}, "meta": {}}, {"expectation_type": "expect_column_values_to_be_null", "kwargs": {"column": "AwayTeam", "mostly": 0}, "meta": {}}, {"expectation_type": "expect_column_values_to_be_of_type", "kwargs": {"column": "FTHG", "type_": "float64"}, "meta": {}}, {"expectation_type": "expect_column_values_to_be_null", "kwargs": {"column": "FTHG", "mostly": 0}, "meta": {}}, {"expectation_type": "expect_column_values_to_be_between", "kwargs": {"column": "FTHG", "min_value": -0.9, "max_value": 9.9}, "meta": {}}, {"expectation_type": "expect_column_values_to_be_of_type", "kwargs": {"column": "FTAG", "type_": "float64"}, "meta": {}}, {"expectation_type": "expect_column_values_to_be_null", "kwargs": {"column": "FTAG", "mostly": 0}, "meta": {}}, {"expectation_type": "expect_column_values_to_be_between", "kwargs": {"column": "FTAG", "min_value": -0.9, "max_value": 9.9}, "meta": {}}, {"expectation_type": "expect_column_values_to_be_of_type", "kwargs": {"column": "FTR", "type_": "str"}, "meta": {}}, {"expectation_type": "expect_column_values_to_be_null", "kwargs": {"column": "FTR", "mostly": 0}, "meta": {}}, {"expectation_type": "expect_column_values_to_be_in_set", "kwargs": {"column": "FTR", "value_set": ["H", "D", "A"]}, "meta": {}}], "expectation_suite_name": "default", "meta": {"great_expectations_version": "0.15.50"}, "data_asset_type": "Dataset"}